README.txt
setup.py
collective/__init__.py
collective.qextendedmenu.egg-info/PKG-INFO
collective.qextendedmenu.egg-info/SOURCES.txt
collective.qextendedmenu.egg-info/dependency_links.txt
collective.qextendedmenu.egg-info/entry_points.txt
collective.qextendedmenu.egg-info/namespace_packages.txt
collective.qextendedmenu.egg-info/not-zip-safe
collective.qextendedmenu.egg-info/paster_plugins.txt
collective.qextendedmenu.egg-info/requires.txt
collective.qextendedmenu.egg-info/top_level.txt
collective/qextendedmenu/__init__.py
collective/qextendedmenu/configure.zcml
collective/qextendedmenu/interfaces.py
collective/qextendedmenu/settings.py
collective/qextendedmenu/tests.py
collective/qextendedmenu/browser/__init__.py
collective/qextendedmenu/browser/configure.zcml
collective/qextendedmenu/browser/forms.py
collective/qextendedmenu/browser/utils.py
collective/qextendedmenu/browser/files/styles.css
collective/qextendedmenu/browser/templates/sections_recurse.pt
collective/qextendedmenu/profiles/default/actions.xml
collective/qextendedmenu/profiles/default/browserlayer.xml
collective/qextendedmenu/profiles/default/cssregistry.xml
collective/qextendedmenu/profiles/default/metadata.xml
collective/qextendedmenu/profiles/default/registry.xml
collective/qextendedmenu/profiles/default/rolemap.xml
docs/HISTORY.txt
docs/INSTALL.txt
docs/LICENSE.GPL
docs/LICENSE.txt