Metadata-Version: 1.0
Name: collective.qextendedmenu
Version: 1.0a1
Summary: extend quintagroup.megameu
Home-page: http://svn.plone.org/svn/collective/
Author: Nathan Van Gheem
Author-email: vangheem@gmail.com
License: GPL
Keywords: menu plone mega
Platform: UNKNOWN
Classifier: Framework :: Plone
Classifier: Programming Language :: Python
